watsonx_rlm_knowledge/__init__.py
watsonx_rlm_knowledge/cli.py
watsonx_rlm_knowledge/client.py
watsonx_rlm_knowledge/context.py
watsonx_rlm_knowledge/engine.py
watsonx_rlm_knowledge/exceptions.py
watsonx_rlm_knowledge/preprocessor.py
watsonx_rlm_knowledge-2.0.0.dist-info/METADATA
watsonx_rlm_knowledge-2.0.0.dist-info/WHEEL
watsonx_rlm_knowledge-2.0.0.dist-info/entry_points.txt
watsonx_rlm_knowledge-2.0.0.dist-info/top_level.txt
watsonx_rlm_knowledge-2.0.0.dist-info/RECORD
