Metadata-Version: 2.4
Name: watsonx-rlm-knowledge
Version: 2.0.0
Summary: RLM-based knowledge client with WatsonX backend for domain-specific document querying
Author-email: Harold Hannon <haroldhannon@gmail.com>
License-Expression: MIT
Project-URL: Homepage, https://github.com/ibivibiv/watsonx-rlm-knowledge
Project-URL: Documentation, https://github.com/ibivibiv/watsonx-rlm-knowledge#readme
Classifier: Development Status :: 4 - Beta
Classifier: Intended Audience :: Developers
Classifier: Programming Language :: Python :: 3
Classifier: Programming Language :: Python :: 3.10
Classifier: Programming Language :: Python :: 3.11
Classifier: Programming Language :: Python :: 3.12
Requires-Python: >=3.10
Requires-Dist: ibm-watsonx-ai>=1.0.0
Requires-Dist: python-docx>=0.8.11
Requires-Dist: pypdf>=3.0.0
Requires-Dist: openpyxl>=3.1.0
Requires-Dist: python-pptx>=0.6.21
Requires-Dist: pydantic>=2.0.0
Requires-Dist: chardet>=5.0.0
Provides-Extra: dev
Requires-Dist: pytest>=7.0.0; extra == "dev"
Requires-Dist: pytest-asyncio>=0.21.0; extra == "dev"
Requires-Dist: black>=23.0.0; extra == "dev"
Requires-Dist: ruff>=0.1.0; extra == "dev"
